core_rest_clients/__init__.py
core_rest_clients/api_client.py
core_rest_clients/api_client_conf.py
core_rest_clients/api_client_exceptions.py
core_rest_clients/api_client_utils.py
core_rest_clients/py.typed
turintech_rest_clients-2.0.0.dist-info/METADATA
turintech_rest_clients-2.0.0.dist-info/WHEEL
turintech_rest_clients-2.0.0.dist-info/licenses/LICENSE
turintech_rest_clients-2.0.0.dist-info/RECORD
