Metadata-Version: 2.4
Name: turintech_rest_clients
Version: 2.0.0
Summary: Functionality for interacting with the REST APIs
License-Expression: LicenseRef-Turing-Intelligence-Technology-EULA
License-File: LICENSE
Classifier: Development Status :: 5 - Production/Stable
Classifier: License :: Other/Proprietary License
Requires-Python: <3.14,>=3.8
Requires-Dist: pydantic<3.0.0,>=2
Requires-Dist: python-dotenv<1.0.0,>=0.21.0
Requires-Dist: requests<3.0.0,>=2.31.0
Requires-Dist: turintech-configuration<3.0.0,>=2.0.0a0
Requires-Dist: turintech-data-types<3.0.0,>=2.0.0a0
Requires-Dist: turintech-exceptions<3.0.0,>=2.0.0a0
Requires-Dist: turintech-logging<3.0.0,>=2.0.0a0
Requires-Dist: turintech-utils<3.0.0,>=2.0.0a0
Requires-Dist: typing-extensions<5.0.0,>=4.5.0
